SearchMaster/__init__.py
SearchMaster-1.1.6.dist-info/LICENSE
SearchMaster-1.1.6.dist-info/METADATA
SearchMaster-1.1.6.dist-info/WHEEL
SearchMaster-1.1.6.dist-info/top_level.txt
SearchMaster-1.1.6.dist-info/RECORD
