Metadata-Version: 2.1
Name: SearchMaster
Version: 1.1.6
Summary: SearchMaster is a Python library that helps you search for files with a specified name across all available drives on your system.
Home-page: https://github.com/deepanshu414/find_allx
Author: Deepanshu antil
Author-email: deepanshuantil4113@gmail.com
Maintainer: Deepanshu antil
License: MIT
License-File: LICENSE
Requires-Dist: psutil
